pdfgen/Topdftool.py
pdfgen/__init__.py
Topdfgen-0.0.2.dist-info/LICENSE.txt
Topdfgen-0.0.2.dist-info/METADATA
Topdfgen-0.0.2.dist-info/WHEEL
Topdfgen-0.0.2.dist-info/top_level.txt
Topdfgen-0.0.2.dist-info/RECORD
